MANIFEST.in
README.md
setup.py
bencode/__init__.py
python_bencode.egg-info/PKG-INFO
python_bencode.egg-info/SOURCES.txt
python_bencode.egg-info/dependency_links.txt
python_bencode.egg-info/pbr.json
python_bencode.egg-info/requires.txt
python_bencode.egg-info/top_level.txt