Metadata-Version: 1.1
Name: python-bencode
Version: 1.0.2
Summary: bencode for humans
Home-page: https://github.com/plasmashadow/pytorrent.git
Author: plasmashadow
Author-email: plasmashadowx@gmail.com
License: BSD License
Platform: UNKNOWN
Classifier: Programming Language :: Python
Classifier: Programming Language :: Python :: 2
Classifier: Intended Audience :: Developers
